[
    { "tester": "4G-01", "status": "run" }
    ,{ "tester": "4G-02", "status": "run" }
    ,{ "tester": "4G-03", "status": "run" }
    ,{ "tester": "4G-04", "status": "run" }
    ,{ "tester": "4G-05", "status": "run" }
    ,{ "tester": "4G-06", "status": "run" }
    ,{ "tester": "4G-07", "status": "run" }
    ,{ "tester": "4G-08", "status": "run" }
    ,{ "tester": "4G-09", "status": "run" }
    ,{ "tester": "4G-10", "status": "poweroff" }
    ,{ "tester": "4G-11", "status": "run" }
    ,{ "tester": "4G-12", "status": "run" }
    ,{ "tester": "4G-13", "status": "run" }
    ,{ "tester": "4G-14", "status": "run" }
    ,{ "tester": "4G-15", "status": "rsp" }
    ,{ "tester": "4G-16", "status": "poweroff" }
    ,{ "tester": "4G-17", "status": "rsp" }
    ,{ "tester": "4G-18", "status": "poweroff" }
    ,{ "tester": "4G-19", "status": "run" }
    ,{ "tester": "4G-20", "status": "run" }
    ,{ "tester": "4G-21", "status": "alert" }
    ,{ "tester": "4G-22", "status": "poweroff" }
    ,{ "tester": "4G-23", "status": "run" }
    ,{ "tester": "4G-24", "status": "run" }
    ,{ "tester": "4G-25", "status": "run" }
    ,{ "tester": "4G-26", "status": "poweroff" }
    ,{ "tester": "4G-27", "status": "run" }
    ,{ "tester": "4G-28", "status": "run" }
    ,{ "tester": "4G-29", "status": "alert" }
    ,{ "tester": "4G-30", "status": "alert" }
    ,{ "tester": "4G-31", "status": "alert" }
    ,{ "tester": "4G-32", "status": "run" }
    ,{ "tester": "4G-33", "status": "alert" }
    ,{ "tester": "4G-34", "status": "run" }
    ,{ "tester": "4G-35", "status": "run" }
    ,{ "tester": "4G-36", "status": "diferent" }
    ,{ "tester": "4G-37", "status": "run" }
    ,{ "tester": "4G-38", "status": "run" }
    ,{ "tester": "4G-39", "status": "run" }
    ,{ "tester": "4G-40", "status": "alert" }
]
